{
  "*EUPBLG": "img",
  "AO*ULTS": "utils",
  "EPBD/*F": "endif",
  "KHR-D": "{:ATTACH:^cd}",
  "KOPBTS": "const",
  "KR*SZ": "css",
  "KWR*PL": "yml",
  "KWRA*RT": "attr",
  "PROBG": "proc",
  "R-PL/R-F": "{:ATTACH:^rm -rf}",
  "R-PL/TK*EUR": "{:ATTACH:^rmdir}",
  "SKWREFPL": "Gemfile",
  "SPH-PT": "smtp",
  "SPH*PT": "{:ATTACH:smtp://}",
  "S-RBG": "src",
  "S*RB": "zsh",
  "ST*R": "str",
  "STKWR-S": "ts",
  "STKWR-SZ": "tsx",
  "T-FRP": "tmp",
  "TPH-FPB": "env",
  "TPH-PL": "npm",
  "TPH*FPB": "ENV",
  "W*GT": "wget"
}
