{
  "KA*RT/*ER/SREUL": "Carterville",
  "KA*RT/ER/SREUL": "Carterville",
  "PESZ/-G": "possessing",
  "PHEUZ/TKPHAOERPB": "misdemeanor",
  "PRAOERLD/HREU": "procedurally",
  "PROEB/-BL": "probable",
  "REZ/-G/A*U": "recognising",
  "SHREPL/HREU": "solemnly",
  "SPWAOEULTD": "entitled",
  "ST*BG/K*L": "statistical",
  "ST*EUBG/K*L": "statistical",
  "STKPAFP/*ER": "dispatcher",
  "STKPHAOERPB/A*U": "misdemeanour",
  "STPHEUPBGTS": "instincts",
  "TOELTD": "totaled",
  "TOELTD/A*U": "totalled",
  "TOET/-LD/A*U": "totalled",
  "TOET/A*L/-D/A*U": "totalled",
  "TOET/ALD/A*U": "totalled",
  "UPB/SAF/REU/A*U": "unsavoury"
}
