{
  "*ERB": "he shall",
  "*UPT": "up the",
  "AO*EURB": "I shall",
  "H*EBG": "he can",
  "HR*E": "will he",
  "HR*UB": "will you be",
  "K*E": "can he",
  "K*UB": "can you be",
  "KWR-RP": "why were",
  "S*UP": "is up",
  "SH*E": "he is",
  "SH*ES": "she's",
  "ST*PBLT": "it is not",
  "ST-PBLT": "is it not",
  "STKHE": "did she",
  "STPH*T": "is in the",
  "TH*ER": "they are",
  "TK*EUG": "did go",
  "TKH*E": "did he",
  "TO*EG": "to go",
  "TPHAOUF": "inform you",
  "TPHO*EUD": "null and void",
  "TPHROT": "are not",
  "W*EBG": "we can",
  "W*EG": "we go",
  "W*US": "with us",
  "WHO*R": "who are",
  "WHUG": "when you go",
  "WHURP": "when you were",
  "WR*U": "were you"
}
